glortrou/__init__.py
glortrou-0.0.0.dist-info/WHEEL
glortrou-0.0.0.dist-info/METADATA
glortrou-0.0.0.dist-info/RECORD
