Metadata-Version: 2.1
Name: glortrou
Version: 0.0.0
Summary: An UDP hole-punching server, client and broker based on AsyncIO
Home-page: https://github.com/frankurcrazy/glortrou
License: BSD-3-Clause
Keywords: udp,hole-punching,p2p,nat,asyncio
Author: Frank Chang
Author-email: frank@csie.io
Requires-Python: >=3.6.1,<4.0.0
Classifier: License :: OSI Approved :: BSD License
Classifier: Programming Language :: Python :: 3
Classifier: Programming Language :: Python :: 3.7
Classifier: Programming Language :: Python :: 3.8
Project-URL: Repository, https://github.com/frankurcrazy/glortrou
